classinet.cpython-38-x86_64-linux-gnu.so
classinet-0.1.dist-info/METADATA
classinet-0.1.dist-info/LICENCE
classinet-0.1.dist-info/WHEEL
classinet-0.1.dist-info/top_level.txt
classinet-0.1.dist-info/RECORD
