Metadata-Version: 2.1
Name: classinet
Version: 0.1
Summary: This is the classinet package
Home-page: http://classinet.com
Author: Yaniv Bargury
Author-email: yaniv@classinet.com
License-File: LICENCE
